{
  "schemaVersion": 1,
  "id": "item-finder",
  "version": "${version}",

  "name": "Item Finder",
  "description": "self explanatory I think",
  "authors": [
    "Vladomeme"
  ],
  "contact": {
  },

  "license": "MIT",
  "icon": "assets/itemfinder/icon.png",

  "environment": "*",
  "entrypoints": {
    "client": [
      "net.itemfinder.main.IFModClient::onInitializeClient"
    ],
    "main": [
      "net.itemfinder.main.IFMod::onInitialize"
    ],
    "modmenu": [
      "net.itemfinder.main.config.IFModMenu"
    ]
  },
  "mixins": [
    "itemfinder.mixins.json"
  ],
  "depends": {
    "fabricloader": ">=0.14.21",
    "fabric": "*",
    "minecraft": "*"
  }
}
